README.rst
httpie_negotiate.py
setup.cfg
setup.py
httpie_negotiate.egg-info/PKG-INFO
httpie_negotiate.egg-info/SOURCES.txt
httpie_negotiate.egg-info/dependency_links.txt
httpie_negotiate.egg-info/entry_points.txt
httpie_negotiate.egg-info/not-zip-safe
httpie_negotiate.egg-info/requires.txt
httpie_negotiate.egg-info/top_level.txt