Metadata-Version: 1.1
Name: httpie-negotiate
Version: 1.0.0
Summary: SPNEGO (GSS Negotiate) auth plugin for HTTPie.
Home-page: https://github.com/ndzou/httpie-negotiate
Author: Nan Zou
Author-email: nanzou@gmail.com
License: BSD
Download-URL: https://github.com/ndzou/httpie-negotiate
Platform: UNKNOWN
Classifier: Development Status :: 5 - Production/Stable
Classifier: Programming Language :: Python
Classifier: Environment :: Plugins
Classifier: License :: OSI Approved :: BSD License
Classifier: Topic :: Internet :: WWW/HTTP
Classifier: Topic :: Utilities
